{
    "booksJson":[
        {
            "id" :"1",
            "title":"The Birth of Tragedy",
            "price":"75000",
            "penulis":"Nietzsche",
            "penerbit":"IRCiSoD",
            "isbn":"978-623-8108-65-7",
            "halaman":"252",
            "img":"./assets/img/The-Birth-of-Tragedy.jpeg",
            "description":"Friedrich Nietzsche (1844–1900) dalam buku ini membeberkan asal-usul tragedi Yunani..",
            "category" :"fiksi",
            "unik" : "satu"
        },
        {
            "id" :"2",
            "title":"Nietzsche dan Islam",
            "price":"75000",
            "penulis":"Roy Jackson",
            "penerbit":"IRCiSoD",
            "isbn":"-",
            "halaman":"412",
            "img":"./assets/img/Nietzsche-Islam.jpeg",
            "description":"Friedrich Nietzsche adalah filsuf masyhur yang kerap diidentikkan dengan ateisme.. ",
            "category" :"fiksi"
        },
        {
            "id" :"3",
            "title":"Genealogi Moral",
            "price":"75000",
            "penulis":"Basabasi",
            "penerbit":"-",
            "isbn":"-",
            "halaman":"220",
            "img":"./assets/img/geneologi-moral.jpeg",
            "description":"Pemikiranku tentang genealogi moral mempunyai bentuk singkat dan.. ",
            "category" :"fiksi"
        },
        {
            "id" :"4",
            "title":"Janji Yang Teringkar",
            "price":"76000",
            "penulis":"Ken Budha Kusumandaru",
            "penerbit":"Instrans Publishing",
            "isbn":"-",
            "halaman":"148",
            "img":"./assets/img/janji-yang-teringkar.jpg",
            "description":"Masyarakat sipil dan organisasi non-pemerintah (NGO) adalah.. ",
            "category" :"non-fiksi"
        },
        {
            "id" :"5",
            "title":"Konsep Judicial Review",
            "price":"80000",
            "penulis":"Ali Marwan HSB",
            "penerbit":"-",
            "isbn":"978-602-6344-19-9",
            "halaman":"200",
            "img":"./assets/img/konsep-judicial-review.jpg",
            "description":"Sebuah produk peraturan perundang-undangan seharusnya...",
            "category" :"non-fiksi"
        },
        {
            "id" :"6",
            "title":"Etnobotani Mangrove",
            "price":"62000",
            "penulis":"Miri Pariyas Tutik Fitriya",
            "penerbit":"-",
            "isbn":"-",
            "halaman":"114",
            "img":"./assets/img/etnobotani-mangrove.jpg",
            "description":"Manusia memiliki hubungan dekat dengan alam, khususnya...",
            "category" :"non-fiksi"
        }
    ]
}